candyfish.py
candyfish-2025.8.2.dist-info/WHEEL
candyfish-2025.8.2.dist-info/METADATA
candyfish-2025.8.2.dist-info/RECORD
