Metadata-Version: 2.4
Name: candyfish
Version: 2025.8.2
Summary: 简易文本训练器
Author-email: Loliyer <271153910@qq.com>
Requires-Python: >=3.10
Requires-Dist: numpy
Requires-Dist: torch
